{"frames": {

"fireball.png":
{
	"frame": {"x":2,"y":2,"w":28,"h":28},
	"rotated": false,
	"trimmed": false,
	"spriteSourceSize": {"x":2,"y":2,"w":28,"h":28},
	"sourceSize": {"w":28,"h":28}
},
"foe.png":
{
	"frame": {"x":32,"y":0,"w":32,"h":32},
	"rotated": false,
	"trimmed": false,
	"spriteSourceSize": {"x":0,"y":0,"w":32,"h":32},
	"sourceSize": {"w":32,"h":32}
},
"player.png":
{
	"frame": {"x":64,"y":0,"w":32,"h":32},
	"rotated": false,
	"trimmed": false,
	"spriteSourceSize": {"x":0,"y":0,"w":32,"h":32},
	"sourceSize": {"w":32,"h":32}
},
"treasure.png":
{
	"frame": {"x":96,"y":0,"w":32,"h":32},
	"rotated": false,
	"trimmed": false,
	"spriteSourceSize": {"x":0,"y":0,"w":32,"h":32},
	"sourceSize": {"w":32,"h":32}
}},
"meta": {
	"app": "https://www.codeandweb.com/texturepacker",
	"version": "1.0",
	"image": "reflex.png",
	"format": "RGBA8888",
	"size": {"w":128,"h":32},
	"scale": "1",
	"smartupdate": "$TexturePacker:SmartUpdate:477f4d17fd00d2a641a958cdc65aeb43:c725cf3ea42ca7c1a6198e73cf1182b9:bdd69564c67c01cca2ccf617ec529748$"
}
}
